MANIFEST.in
README.rst
setup.py
archelond/__init__.py
archelond/config.py
archelond/log.py
archelond/util.py
archelond/web.py
archelond.egg-info/PKG-INFO
archelond.egg-info/SOURCES.txt
archelond.egg-info/dependency_links.txt
archelond.egg-info/entry_points.txt
archelond.egg-info/not-zip-safe
archelond.egg-info/requires.txt
archelond.egg-info/top_level.txt
archelond/data/__init__.py
archelond/data/abstract.py
archelond/data/elastic.py
archelond/data/memory.py
archelond/static/.gitignore
archelond/static/css/bootstrap.css.map
archelond/static/css/bootstrap.min.css
archelond/static/css/datatables.bootstrap.css
archelond/static/css/site.css
archelond/static/fonts/glyphicons-halflings-regular.eot
archelond/static/fonts/glyphicons-halflings-regular.svg
archelond/static/fonts/glyphicons-halflings-regular.ttf
archelond/static/fonts/glyphicons-halflings-regular.woff
archelond/static/images/back_disabled.png
archelond/static/images/back_enabled.png
archelond/static/images/back_enabled_hover.png
archelond/static/images/forward_disabled.png
archelond/static/images/forward_enabled.png
archelond/static/images/forward_enabled_hover.png
archelond/static/images/header.png
archelond/static/images/sort_asc.png
archelond/static/images/sort_asc_disabled.png
archelond/static/images/sort_both.png
archelond/static/images/sort_desc.png
archelond/static/images/sort_desc_disabled.png
archelond/static/images/favicons/apple-touch-icon-114x114.png
archelond/static/images/favicons/apple-touch-icon-120x120.png
archelond/static/images/favicons/apple-touch-icon-144x144.png
archelond/static/images/favicons/apple-touch-icon-152x152.png
archelond/static/images/favicons/apple-touch-icon-180x180.png
archelond/static/images/favicons/apple-touch-icon-57x57.png
archelond/static/images/favicons/apple-touch-icon-60x60.png
archelond/static/images/favicons/apple-touch-icon-72x72.png
archelond/static/images/favicons/apple-touch-icon-76x76.png
archelond/static/images/favicons/apple-touch-icon-precomposed.png
archelond/static/images/favicons/apple-touch-icon.png
archelond/static/images/favicons/browserconfig.xml
archelond/static/images/favicons/favicon-160x160.png
archelond/static/images/favicons/favicon-16x16.png
